pytauri_plugin_notification/__init__.py
pytauri_plugin_notification/ffi.py
pytauri_plugin_notification/py.typed
pytauri_plugin_notification-0.5.0.dist-info/METADATA
pytauri_plugin_notification-0.5.0.dist-info/WHEEL
pytauri_plugin_notification-0.5.0.dist-info/RECORD
