Metadata-Version: 2.4
Name: pytauri-plugin-notification
Version: 0.5.0
Summary: tauri-plugin-notification binding for PyTauri.
Project-URL: documentation, https://pytauri.github.io/pytauri/
Project-URL: source, https://github.com/pytauri/pytauri
Author-email: Sean Wang <126865849+WSH032@users.noreply.github.com>
License-Expression: Apache-2.0
Requires-Python: >=3.9
Requires-Dist: pytauri==0.5.*
Requires-Dist: typing-extensions>=4
